<?xml version="1.0" encoding="UTF-8" ?>
<localize>

 
  <!-- day31 start -->


  <text id="day31_a_1">迷霧之中, 混雜了尖叫與咆嘯, 沒人可以肯定是否是迷霧導致了瘋狂, 或是叫聲製造了迷霧.</text>
  <text id="day31_b_1">你現在開始研究機器了嗎?</text>
  <text id="day31_b_2">那太好了, 在我眼前有個萬事通.</text>
  <text id="day31_b_3">坦白說, 我覺得我自己也挺行的.</text>
  <text id="day31_b_4">但是看著你這樣, 這讓我覺得我之前對自己太過自滿了.</text>
  <text id="day31_b_5">….</text>
  <text id="day31_b_6">讓我幫你一把吧, 不會怎麼樣的?</text>
  <text id="day31_b_7">我會當個稱職的助手的.</text>
  <text id="day31_b_8">很開心看到你振作起來了. </text>
  <text id="day31_b_9">能與一個我敬仰的學者共識絕對是我的榮幸. </text>
  <text id="day31_b_10">怎麼了?</text>
  <text id="day31_b_11">.... 你沒事吧?</text>
  
  <text id="day31_angela_1">你真的不太好, 對吧?</text>
  <text id="day31_angela_2">如果你在陽光觸碰到你時想起那些種種而崩潰,</text>
  <text id="day31_angela_3">以及看到外面的植披讓你莫名憤怒失去理智,</text>
  <text id="day31_angela_4">那我們別無選擇只能待在地底.</text>
  <text id="day31_angela_5">讓我們從頭來過, 在 Lobotomy 緬懷她. </text>
 



</localize>
